Metadata-Version: 2.2
Name: simasm
Version: 0.4.4
Summary: Abstract State Machine Framework for Discrete Event Simulation
Author: Steve Yeo
License: MIT
Project-URL: Homepage, https://simasm-project.github.io/
Project-URL: Documentation, https://simasm-project.github.io/reference/syntax.html/
Project-URL: Repository, https://github.com/SimASM-Project
Project-URL: Issues, https://github.com/SimASM-Project/simasm/issues
Keywords: simulation,discrete-event,state-machine,verification,event-graph,activity-cycle-diagram,stutter-equivalence
Classifier: Development Status :: 3 - Alpha
Classifier: Intended Audience :: Science/Research
Classifier: Intended Audience :: Developers
Classifier: Operating System :: OS Independent
Classifier: Programming Language :: Python :: 3
Classifier: Programming Language :: Python :: 3.9
Classifier: Programming Language :: Python :: 3.10
Classifier: Programming Language :: Python :: 3.11
Classifier: Programming Language :: Python :: 3.12
Classifier: Topic :: Scientific/Engineering
Classifier: Topic :: Scientific/Engineering :: Mathematics
Classifier: Topic :: Software Development :: Interpreters
Requires-Python: >=3.9
License-File: LICENSE
Requires-Dist: lark>=1.1.0
Requires-Dist: pydantic>=2.0
Requires-Dist: numpy>=1.20
Requires-Dist: matplotlib==3.9.2
Requires-Dist: scipy>=1.9
Provides-Extra: jupyter
Requires-Dist: ipython>=7.0; extra == "jupyter"
Requires-Dist: matplotlib-inline>=0.1.6; extra == "jupyter"
Provides-Extra: dev
Requires-Dist: pytest>=7.0; extra == "dev"
Requires-Dist: pytest-cov>=4.0; extra == "dev"
Requires-Dist: build>=1.0; extra == "dev"
Requires-Dist: twine>=4.0; extra == "dev"
Provides-Extra: all
Requires-Dist: simasm[dev,jupyter]; extra == "all"
